carbone_connect/__init__.py
carbone_connect/client.py
py_carbone_connect-1.1.2.dist-info/LICENSE
py_carbone_connect-1.1.2.dist-info/METADATA
py_carbone_connect-1.1.2.dist-info/WHEEL
py_carbone_connect-1.1.2.dist-info/top_level.txt
py_carbone_connect-1.1.2.dist-info/RECORD
