Metadata-Version: 2.1
Name: py-carbone-connect
Version: 1.1.2
Summary: A Python client for the Carbone API
Home-page: https://github.com/Piuliss/py-carbone-connect
Author: Raul B. Netto
Author-email: raulbeni@gmail.com
Project-URL: Bug Reports, https://github.com/Piuliss/py-carbone-connect/issues
Project-URL: Source, https://github.com/Piuliss/py-carbone-connect
Classifier: Development Status :: 3 - Alpha
Classifier: Intended Audience :: Developers
Classifier: License :: OSI Approved :: MIT License
Classifier: Operating System :: OS Independent
Classifier: Programming Language :: Python :: 3
Classifier: Programming Language :: Python :: 3.7
Classifier: Programming Language :: Python :: 3.8
Classifier: Programming Language :: Python :: 3.9
Classifier: Programming Language :: Python :: 3.10
Classifier: Programming Language :: Python :: 3.11
Requires-Python: >=3.7
License-File: LICENSE
Requires-Dist: requests>=2.25.0
Provides-Extra: dev
Requires-Dist: pytest>=6.0; extra == "dev"
Requires-Dist: pytest-cov>=2.0; extra == "dev"
Requires-Dist: pytest-mock>=3.6; extra == "dev"
Requires-Dist: black>=22.0; extra == "dev"
Requires-Dist: isort>=5.0; extra == "dev"
Requires-Dist: mypy>=0.900; extra == "dev"
Requires-Dist: flake8>=3.9; extra == "dev"
